MANIFEST.in
README.rst
bootstrap.py
buildout.cfg
setup.py
maskattack/__init__.py
maskattack.study.egg-info/PKG-INFO
maskattack.study.egg-info/SOURCES.txt
maskattack.study.egg-info/dependency_links.txt
maskattack.study.egg-info/entry_points.txt
maskattack.study.egg-info/namespace_packages.txt
maskattack.study.egg-info/not-zip-safe
maskattack.study.egg-info/requires.txt
maskattack.study.egg-info/top_level.txt
maskattack/study/__init__.py
maskattack/study/accumulate/__init__.py
maskattack/study/accumulate/accumulated_to_depth.py
maskattack/study/accumulate/hdf5_to_grayscale.py
maskattack/study/accumulate/rgbd_to_rgbxyz.py
maskattack/study/accumulate/rgbxyz_to_accumulated.py
maskattack/study/accumulate/view_accumulated.py
maskattack/study/analyze/__init__.py
maskattack/study/analyze/ext.cpp
maskattack/study/analyze/gen.obj
maskattack/study/analyze/gen_pts.txt
maskattack/study/analyze/icp.py
maskattack/study/analyze/isv.py
maskattack/study/analyze/lbp.py
maskattack/study/analyze/plot.py
maskattack/study/analyze/tps.py
maskattack/study/antispoof/__init__.py
maskattack/study/antispoof/lbp.py
maskattack/study/antispoof/plot.py