Metadata-Version: 1.1
Name: maskattack.study
Version: 1.0.0
Summary: Accumulate depth frames of 3DMAD database for better face models and analyze verification and spoofing performances of 2D, 2.5D and 3D samples
Home-page: http://github.com/bioidiap/maskattack.study
Author: Nesli Erdogmus
Author-email: nesli.erdogmus@idiap.ch
License: GPLv3
Platform: UNKNOWN
Classifier: Development Status :: 4 - Beta
Classifier: Intended Audience :: Developers
Classifier: License :: OSI Approved :: GNU General Public License v3 (GPLv3)
Classifier: Natural Language :: English
Classifier: Programming Language :: Python
